{"trial_id": "01", "hyperparameters": {"space": [{"class_name": "Int", "config": {"name": "num_layers", "default": null, "conditions": [], "min_value": 1, "max_value": 3, "step": 1, "sampling": "linear"}}, {"class_name": "Int", "config": {"name": "units_0", "default": null, "conditions": [], "min_value": 32, "max_value": 128, "step": 32, "sampling": "linear"}}, {"class_name": "Boolean", "config": {"name": "dropout", "default": false, "conditions": []}}, {"class_name": "Choice", "config": {"name": "optimizer", "default": "adam", "conditions": [], "values": ["adam", "rmsprop"], "ordered": false}}, {"class_name": "Int", "config": {"name": "units_1", "default": null, "conditions": [], "min_value": 32, "max_value": 128, "step": 32, "sampling": "linear"}}, {"class_name": "Int", "config": {"name": "units_2", "default": null, "conditions": [], "min_value": 32, "max_value": 128, "step": 32, "sampling": "linear"}}], "values": {"num_layers": 2, "units_0": 64, "dropout": false, "optimizer": "adam", "units_1": 32, "units_2": 64}}, "metrics": {"metrics": {"loss": {"direction": "min", "observations": [{"value": [0.05479772761464119], "step": 11}]}, "accuracy": {"direction": "max", "observations": [{"value": [0.9828125238418579], "step": 11}]}, "val_loss": {"direction": "min", "observations": [{"value": [0.09543700516223907], "step": 11}]}, "val_accuracy": {"direction": "max", "observations": [{"value": [0.96875], "step": 11}]}}}, "score": 0.96875, "best_step": 11, "status": "COMPLETED", "message": null}